calculator/__init__.py
calculator/calculator.py
calculator_james/__init__.py
calculator_james/calculator.py
calculator_james-0.1.0.dist-info/METADATA
calculator_james-0.1.0.dist-info/WHEEL
calculator_james-0.1.0.dist-info/top_level.txt
calculator_james-0.1.0.dist-info/RECORD
