Metadata-Version: 2.1
Name: calculator_james
Version: 0.1.0
Summary: A small test example package
Home-page: https://git.labs.hosting.cerence.net/james.chang/pypi_package
Author: James
Author-email: james.chang@cerence.com
Classifier: Programming Language :: Python :: 3
Classifier: License :: OSI Approved :: MIT License
Classifier: Operating System :: OS Independent
Requires-Python: >=3.6
